<contatos>
    <contato>
        <nome>Joao Silva</nome>
        <email>joao@gmail.com</email>
    </contato>
    <contato>
        <nome>Maria Rita</nome>
        <email>maria@gmail.com</email>
    </contato>
    <contato>
        <nome>Julia Laura</nome>
        <email>julia@gmail.com</email>
    </contato>
    <contato>
        <nome>Paulo Afonso</nome>
        <email>p.afonso@gmail.com</email>
    </contato>
    <contato>
        <nome>Roberto Carlos</nome>
        <email>r.carlos@gmail.com</email>
    </contato>
</contatos>